fluvialgen/__init__.py
fluvialgen/base_generator.py
fluvialgen/csv_dataset_generator.py
fluvialgen/csv_past_forecast_batcher.py
fluvialgen/movingwindow_generator.py
fluvialgen/past_forecast_batcher.py
fluvialgen/river_dataset_generator.py
fluvialgen/tests/__init__.py
fluvialgen/tests/test_csv_dataset_generator.py
fluvialgen/tests/test_csv_past_forecast_batcher.py
fluvialgen/tests/test_movingwindow_batcher.py
fluvialgen/tests/test_past_forecast_batcher.py
fluvialgen-1.1.0.dist-info/METADATA
fluvialgen-1.1.0.dist-info/WHEEL
fluvialgen-1.1.0.dist-info/top_level.txt
fluvialgen-1.1.0.dist-info/RECORD
