Metadata-Version: 2.4
Name: fluvialgen
Version: 1.1.0
Summary: A Python package for generating synthetic river networks and datasets
Home-page: https://github.com/joseenriqueruiznavarro/FluvialGen
Author: Jose Enrique Ruiz Navarro
Author-email: Jose Enrique Ruiz Navarro <joseenriqueruiznavarro@gmail.com>
Classifier: Development Status :: 3 - Alpha
Classifier: Intended Audience :: Science/Research
Classifier: License :: OSI Approved :: MIT License
Classifier: Programming Language :: Python :: 3.12
Classifier: Programming Language :: Python :: 3.13
Requires-Python: >=3.8
Dynamic: author
Dynamic: home-page
Dynamic: requires-python
